SciExpeM_API/SciExpeM.py
SciExpeM_API/__init__.py
SciExpeM_API/Models/ChemModel.py
SciExpeM_API/Models/CommonProperty.py
SciExpeM_API/Models/CurveMatchingResult.py
SciExpeM_API/Models/DataColumn.py
SciExpeM_API/Models/Execution.py
SciExpeM_API/Models/ExecutionColumn.py
SciExpeM_API/Models/Experiment.py
SciExpeM_API/Models/ExperimentBackUp.py
SciExpeM_API/Models/ExperimentInterpreter.py
SciExpeM_API/Models/FilePaper.py
SciExpeM_API/Models/InitialSpecie.py
SciExpeM_API/Models/InitialSpecies.py
SciExpeM_API/Models/MappingInterpreter.py
SciExpeM_API/Models/RuleInterpreter.py
SciExpeM_API/Models/Specie.py
SciExpeM_API/Models/Species.py
SciExpeM_API/Models/__init__.py
SciExpeM_API/Utility/QSerializer.py
SciExpeM_API/Utility/RequestAPI.py
SciExpeM_API/Utility/Tools.py
SciExpeM_API/Utility/User.py
SciExpeM_API/Utility/__init__.py
SciExpeM_API/Utility/exceptionsAPI.py
SciExpeM_API/Utility/settings.py
SciExpeM_API/Views/_ExperimentManager.py
SciExpeM_API/Views/_ReSpecTh.py
SciExpeM_API/Views/__OpenSmoke.py
SciExpeM_API/Views/__init__.py
SciExpeM_ReSpecTh/SciExpeM_ReSpecTh.py
SciExpeM_ReSpecTh/__init__.py
SciExpeM_API-2.0.3.5.dist-info/METADATA
SciExpeM_API-2.0.3.5.dist-info/WHEEL
SciExpeM_API-2.0.3.5.dist-info/top_level.txt
SciExpeM_API-2.0.3.5.dist-info/RECORD
