Metadata-Version: 2.1
Name: SciExpeM-API
Version: 2.0.3.5
Summary: Python wrapper for SciExpeM EndPoints
Home-page: https://github.com/edoardoramalli/SciExpeM_API
Author: Edoardo Ramalli
Author-email: edoardo.ramalli@polimi.it
Classifier: Programming Language :: Python :: 3
Classifier: Operating System :: OS Independent
Classifier: Topic :: Scientific/Engineering
Classifier: Topic :: Scientific/Engineering :: Chemistry
Classifier: Topic :: Scientific/Engineering :: Information Analysis
Classifier: Topic :: Software Development :: Interpreters
Classifier: Topic :: Software Development :: Libraries :: Application Frameworks
Requires-Dist: requests
Requires-Dist: django
Requires-Dist: simplejson
Requires-Dist: pandas
